{
    "Kunde1": {
        "firstName": "Yannick",
        "lastName": "Spangel",
        "enabled": true,
        "address": {
            "street": "Frintroper Str. 70",
            "city": "Essen",
            "zip": "45359",
            "country": "Germany"
        },
        "salesAmount": 12345.6789,
        "currencyCode": "EUR"
    },

    "Kunde2": {
        "firstName": "Raphael",
        "lastName": "Jannes",
        "enabled": false,
        "address": {
            "street": "Raphaels Straße 1",
            "city": "Mülheim",
            "zip": "45468",
            "country": "Germany"
        },
        "salesAmount": 98765.4321
    },
    "currencyCode": "EUR",
    "priceThreshold": 20
}
